pyalgorand/__init__.py
pyalgorand/account.py
pyalgorand/account_manager.py
pyalgorand/connector.py
pyalgorand/ipfs.py
pyalgorand/main.py
pyalgorand/settings.py
pyalgorand/transactor.py
pyalgorand/utils.py
pyalgorand-0.1.0.dist-info/METADATA
pyalgorand-0.1.0.dist-info/WHEEL
pyalgorand-0.1.0.dist-info/top_level.txt
pyalgorand-0.1.0.dist-info/RECORD
