Metadata-Version: 2.1
Name: pyalgorand
Version: 0.1.0
Summary: UNKNOWN
Home-page: https://bitbucket.org/kuiristo/pyalgorand
Author: Jean-Baptiste Poullet
Author-email: jeanbaptistepoullet@gmail.com
License: Apache Software License 2.0
Platform: UNKNOWN
Requires-Dist: py-algorand-sdk (>=1.4.1)
Requires-Dist: apscheduler (>=3.6.3)
Requires-Dist: ipfshttpclient (>=0.7.0)
Requires-Dist: pyyaml (>=5.4.1)
Provides-Extra: docs
Requires-Dist: sphinx (~=3.4.3) ; extra == 'docs'
Requires-Dist: sphinx-rtd-theme (==0.5.1) ; extra == 'docs'
Requires-Dist: nbsphinx (==0.8.1) ; extra == 'docs'
Requires-Dist: nbstripout (==0.3.3) ; extra == 'docs'
Requires-Dist: recommonmark (==0.7.1) ; extra == 'docs'
Requires-Dist: sphinx-autodoc-typehints (==1.11.1) ; extra == 'docs'
Requires-Dist: sphinx-copybutton (==0.3.1) ; extra == 'docs'
Requires-Dist: ipykernel (~=5.3) ; extra == 'docs'
